munigeo/__init__.py
munigeo/api.py
munigeo/apps.py
munigeo/models.py
munigeo/ocd.py
munigeo/oldapi.py
munigeo/tests.py
munigeo/utils.py
munigeo/views.py
munigeo/data/fi/helsinki/config.yml
munigeo/importer/__init__.py
munigeo/importer/athens.py
munigeo/importer/base.py
munigeo/importer/finland.py
munigeo/importer/helsinki.py
munigeo/importer/manchester.py
munigeo/importer/sync.py
munigeo/management/__init__.py
munigeo/management/commands/__init__.py
munigeo/management/commands/geo_import.py
munigeo/migrations/0001_squashed_0004_building.py
munigeo/migrations/0002_add_parler_translations.py
munigeo/migrations/0003_migrate_translations_to_parler.py
munigeo/migrations/0004_delete_old_translations.py
munigeo/migrations/0005_update_translation_foreign_keys.py
munigeo/migrations/__init__.py
munigeo/tests/__init__.py
munigeo/tests/conftest.py
munigeo/tests/test_syncher.py
django_munigeo-0.3.12.dist-info/LICENSE
django_munigeo-0.3.12.dist-info/METADATA
django_munigeo-0.3.12.dist-info/WHEEL
django_munigeo-0.3.12.dist-info/top_level.txt
django_munigeo-0.3.12.dist-info/RECORD
