Metadata-Version: 2.2
Name: django-munigeo
Version: 0.3.12
Summary: A Django app for processing municipality-related geospatial data.
Home-page: https://github.com/City-of-Helsinki/django-munigeo
Author: City of Helsinki
Author-email: dev@hel.fi
License: BSD License
Classifier: Environment :: Web Environment
Classifier: Framework :: Django
Classifier: Intended Audience :: Developers
Classifier: License :: OSI Approved :: BSD License
Classifier: Operating System :: OS Independent
Classifier: Programming Language :: Python
Classifier: Programming Language :: Python :: 3
Classifier: Programming Language :: Python :: 3.2
Classifier: Programming Language :: Python :: 3.3
Classifier: Programming Language :: Python :: 3.4
Classifier: Programming Language :: Python :: 3.5
Classifier: Programming Language :: Python :: 3.6
Classifier: Topic :: Internet :: WWW/HTTP
Classifier: Topic :: Internet :: WWW/HTTP :: Dynamic Content
Classifier: Topic :: Scientific/Engineering :: GIS
License-File: LICENSE
Requires-Dist: Django
Requires-Dist: requests
Requires-Dist: requests_cache
Requires-Dist: django_mptt
Requires-Dist: django-parler>=2
Requires-Dist: django-parler-rest
Requires-Dist: six
Requires-Dist: pyyaml
Dynamic: author
Dynamic: author-email
Dynamic: classifier
Dynamic: description
Dynamic: description-content-type
Dynamic: home-page
Dynamic: license
Dynamic: requires-dist
Dynamic: summary
